mtmdb/__init__.py
mtmdb/__main__.py
mtmdb/datasets.py
mtmdb-0.0.802.dist-info/METADATA
mtmdb-0.0.802.dist-info/WHEEL
mtmdb-0.0.802.dist-info/RECORD
