Metadata-Version: 2.1
Name: mtmdb
Version: 0.0.802
Summary: 
License: MIT
Author: John Smith
Author-email: john@example.com
Requires-Python: >=3.10,<3.13
Classifier: License :: OSI Approved :: MIT License
Classifier: Programming Language :: Python :: 3
Classifier: Programming Language :: Python :: 3.10
Classifier: Programming Language :: Python :: 3.11
Classifier: Programming Language :: Python :: 3.12
Requires-Dist: fastapi (>=0.104.1)
Requires-Dist: httpx (>=0.27.0,<0.28.0)
Requires-Dist: nanoid (>=2.0.0,<3.0.0)
Requires-Dist: opentelemetry-api (>=1.26.0,<2.0.0)
Requires-Dist: opentelemetry-exporter-otlp-proto-http (>=1.26.0,<2.0.0)
Requires-Dist: opentelemetry-instrumentation-fastapi (>=0.47b0,<0.48)
Requires-Dist: opentelemetry-instrumentation-logging (>=0.47b0,<0.48)
Requires-Dist: opentelemetry-sdk (>=1.26.0,<2.0.0)
Requires-Dist: pydantic (>=2.5.1)
Requires-Dist: python-dotenv (>=1.0.0)
Requires-Dist: sqlmodel (>=0.0.21,<0.0.22)
